cnki_agent/__init__.py
cnki_agent/agent.py
cnki_agent-0.1.2.dist-info/LICENSE
cnki_agent-0.1.2.dist-info/METADATA
cnki_agent-0.1.2.dist-info/WHEEL
cnki_agent-0.1.2.dist-info/top_level.txt
cnki_agent-0.1.2.dist-info/RECORD
